LICENSE
MANIFEST.in
README.md
requirements.txt
setup.py
pyformanceanalytics/CDD.py
pyformanceanalytics/ETL.py
pyformanceanalytics/ETL_clean.py
pyformanceanalytics/ETL_method.py
pyformanceanalytics/ETL_portfolio_method.py
pyformanceanalytics/M2_sortino.py
pyformanceanalytics/VaR.py
pyformanceanalytics/__init__.py
pyformanceanalytics/active_premium.py
pyformanceanalytics/adjusted_sharpe_ratio.py
pyformanceanalytics/appraisal_ratio.py
pyformanceanalytics/appraisal_ratio_method.py
pyformanceanalytics/average_drawdown.py
pyformanceanalytics/average_length.py
pyformanceanalytics/average_recovery.py
pyformanceanalytics/bernardo_ledoit_ratio.py
pyformanceanalytics/beta_co_kurtosis.py
pyformanceanalytics/beta_co_skewness.py
pyformanceanalytics/beta_co_variance.py
pyformanceanalytics/burke_ratio.py
pyformanceanalytics/calculate_return_method.py
pyformanceanalytics/calculate_returns.py
pyformanceanalytics/calmar_ratio.py
pyformanceanalytics/centeredcomoment.py
pyformanceanalytics/centeredmoment.py
pyformanceanalytics/co_kurtosis.py
pyformanceanalytics/co_kurtosis_matrix.py
pyformanceanalytics/co_skewness.py
pyformanceanalytics/co_skewness_matrix.py
pyformanceanalytics/co_variance.py
pyformanceanalytics/d_ratio.py
pyformanceanalytics/downside_deviation.py
pyformanceanalytics/downside_deviation_method.py
pyformanceanalytics/downside_frequency.py
pyformanceanalytics/downside_potential.py
pyformanceanalytics/drawdown_deviation.py
pyformanceanalytics/drawdown_peak.py
pyformanceanalytics/drawdowns.py
pyformanceanalytics/fama_beta.py
pyformanceanalytics/find_drawdowns.py
pyformanceanalytics/frequency.py
pyformanceanalytics/hurst_index.py
pyformanceanalytics/information_ratio.py
pyformanceanalytics/kappa.py
pyformanceanalytics/kelly_ratio.py
pyformanceanalytics/kurtosis.py
pyformanceanalytics/kurtosis_method.py
pyformanceanalytics/lpm.py
pyformanceanalytics/m_squared.py
pyformanceanalytics/m_squared_excess.py
pyformanceanalytics/m_squared_excess_method.py
pyformanceanalytics.egg-info/PKG-INFO
pyformanceanalytics.egg-info/SOURCES.txt
pyformanceanalytics.egg-info/dependency_links.txt
pyformanceanalytics.egg-info/not-zip-safe
pyformanceanalytics.egg-info/requires.txt
pyformanceanalytics.egg-info/top_level.txt
