Metadata-Version: 2.1
Name: pyformanceanalytics
Version: 0.0.5
Summary: A python wrapper around the PerformanceAnalytics R code.
Home-page: https://github.com/8W9aG/pyformanceanalytics
Author: Will Sackfield
Author-email: will.sackfield@gmail.com
License: GPL2
Keywords: r performanceanalytics
Classifier: License :: OSI Approved :: GNU General Public License v2 (GPLv2)
Classifier: Programming Language :: Python :: 3
License-File: LICENSE
Requires-Dist: rpy2>=3.5.15
Requires-Dist: pandas>=2.1.4
Requires-Dist: pillow>=10.2.0
Requires-Dist: numpy>=1.26.3
